linear_segmentation/__init__.py
linear_segmentation/linear_segmentation.py
linear_segmentation/examples/__init__.py
linear_segmentation/examples/linear_segmentation_with_slider.py
linear_segmentation-0.2.post2.dist-info/LICENSE
linear_segmentation-0.2.post2.dist-info/METADATA
linear_segmentation-0.2.post2.dist-info/WHEEL
linear_segmentation-0.2.post2.dist-info/top_level.txt
linear_segmentation-0.2.post2.dist-info/RECORD
