Metadata-Version: 2.1
Name: linear-segmentation
Version: 0.2.post2
Summary: Automatic sparse sampling of 1-D array into linear segments minimizing error
Home-page: http://github.com/andermi/linear_segmentation
Author: Michael Anderson
Author-email: manders9@jhu.edu
License: MIT
Platform: UNKNOWN
Requires-Python: >=3
License-File: LICENSE
Requires-Dist: numpy
Requires-Dist: scipy
Requires-Dist: matplotlib
Requires-Dist: tqdm
